ami_val/__init__.py
ami_val/ami_val.py
ami_val/cfg/ami-val.yaml
ami_val/libs/__init__.py
ami_val/libs/aws_lib.py
ami_val/libs/resource_class.py
ami_val/libs/utils_lib.py
ami_val/scripts/rhel-ha-aws-check.sh
ami_val/templates/sum.html
ami_val/tests/__init__.py
ami_val/tests/test_stage0.py
ami_val/tests/test_stage1.py
ami_val/tests/test_stage2.py
ami_val/tests/test_stage3.py
ami_val-0.3.0.dist-info/METADATA
ami_val-0.3.0.dist-info/WHEEL
ami_val-0.3.0.dist-info/entry_points.txt
ami_val-0.3.0.dist-info/top_level.txt
ami_val-0.3.0.dist-info/RECORD
