Metadata-Version: 2.1
Name: ami-val
Version: 0.3.0
Summary: AMI validation tool
Home-page: https://github.com/liangxiao1/ami-val
Author: Xiao Liang
Author-email: xiliang@redhat.com
License: GPLv3+
Classifier: License :: OSI Approved :: GNU General Public License v3 or later (GPLv3+)
Classifier: Programming Language :: Python :: 3
Classifier: Operating System :: POSIX
Requires-Python: >=3.6
Requires-Dist: PyYAML
Requires-Dist: tipset >=0.0.12
Requires-Dist: filelock
Requires-Dist: awscli
Requires-Dist: boto3
Requires-Dist: paramiko
Requires-Dist: Jinja2
